Metadata-Version: 1.0
Name: akash-distributions
Version: 0.1
Summary: Adding two numbers
Home-page: UNKNOWN
Author: Akash Selvakumar
Author-email: akashselvae7@gmail.com
License: UNKNOWN
Platform: UNKNOWN
